[
    {
        "id": 1775733784542,
        "nickname": "ᗜ v ᗜ",
        "user_id": 1,
        "content": "高等代数好难啊，好不想学习啊，好想赶紧赚钱，好像过个人的生活",
        "area": "personal",
        "partition": null,
        "timestamp": "2026-04-09 19:23:04",
        "comments": []
    },
    {
        "id": 1775734727807,
        "nickname": "ᗜ v ᗜ",
        "user_id": 1,
        "content": "不是，hzq的课是真水吧，都没什么人去了",
        "area": "personal",
        "partition": null,
        "timestamp": "2026-04-09 19:38:47",
        "comments": []
    },
    {
        "id": 1775993924541,
        "nickname": "ᗜ v ᗜ",
        "user_id": 1,
        "content": "我现在很生气！手现在抖个不停！",
        "area": "personal",
        "partition": null,
        "timestamp": "2026-04-12 19:38:44",
        "comments": []
    }
]